CloudflareAPI/__init__.py
CloudflareAPI/__version__.py
CloudflareAPI/cloudflare.py
CloudflareAPI/exceptions.py
CloudflareAPI/utils.py
CloudflareAPI/api/__init__.py
CloudflareAPI/api/account.py
CloudflareAPI/api/storage.py
CloudflareAPI/api/user.py
CloudflareAPI/api/worker/__init__.py
CloudflareAPI/api/worker/core.py
CloudflareAPI/api/worker/cron.py
CloudflareAPI/api/worker/subdomain.py
CloudflareAPI/core/__init__.py
CloudflareAPI/core/base.py
CloudflareAPI/core/configuration.py
CloudflareAPI/core/network.py
CloudflareAPI/dataclass/__init__.py
CloudflareAPI/dataclass/account.py
CloudflareAPI/dataclass/namespace.py
CloudflareAPI/dataclass/user.py
cloudflare_api-2.1.0.dist-info/LICENSE
cloudflare_api-2.1.0.dist-info/METADATA
cloudflare_api-2.1.0.dist-info/WHEEL
cloudflare_api-2.1.0.dist-info/top_level.txt
cloudflare_api-2.1.0.dist-info/RECORD
