Metadata-Version: 2.1
Name: cloudflare-api
Version: 2.1.0
Summary: Python client for the Cloudflare v4 API
Home-page: https://github.com/nikhiljohn10/cloudflare-api
Author: Nikhil John
Author-email: nikhiljohn1010@gmail.com
License: MIT
Keywords: cloudflare-api
Platform: UNKNOWN
Classifier: Development Status :: 5 - Production/Stable
Classifier: Intended Audience :: Developers
Classifier: Topic :: Software Development :: Libraries :: Python Modules
Classifier: License :: OSI Approved :: MIT License
Classifier: Programming Language :: Python :: 3
Classifier: Programming Language :: Python :: 3.9
Requires-Dist: requests
